pynum/__init__.py
pynum/fact.py
pynum-0.0.1.dist-info/METADATA
pynum-0.0.1.dist-info/WHEEL
pynum-0.0.1.dist-info/top_level.txt
pynum-0.0.1.dist-info/RECORD
