Metadata-Version: 2.1
Name: pynum
Version: 0.0.1
Summary: Playing with packages
Home-page: https://github.com/Arunima505/pynum
Author: Arunima Bhattacharya
Author-email: UNKNOWN
License: UNKNOWN
Platform: UNKNOWN
Classifier: Programming Language :: Python :: 3
Classifier: Operating System :: OS Independent
Requires-Python: >=3.6
